prslink/__init__.py
prslink/g_Log.py
prslink/g_PRS_object.py
prslink/g_version.py
prslink/io_download_PGS.py
prslink/io_load_data.py
prslink/io_load_plink.py
prslink/io_save.py
prslink/model_elastic_net.py
prslink/model_evaluate.py
prslink/qc.py
prslink/util_r2_conversion.py
prslink/visualization.py
prslink/visualization_auxiliary.py
prslink-0.0.1.dist-info/LICENSE
prslink-0.0.1.dist-info/METADATA
prslink-0.0.1.dist-info/WHEEL
prslink-0.0.1.dist-info/top_level.txt
prslink-0.0.1.dist-info/RECORD
